CHANGES.txt
MANIFEST.in
README.txt
setup.py
casava/__init__.py
casava/reader_impl.py
casava.egg-info/PKG-INFO
casava.egg-info/SOURCES.txt
casava.egg-info/dependency_links.txt
casava.egg-info/entry_points.txt
casava.egg-info/not-zip-safe
casava.egg-info/requires.txt
casava.egg-info/top_level.txt
casava/tests/__init__.py
casava/tests/test_functional.py