Metadata-Version: 1.0
Name: casava
Version: 0.1
Summary: casava: a csv reader thingy
Home-page: https://github.com/synappio/casava
Author: Rick Copeland
Author-email: rick@arborian.com
License: UNKNOWN
Keywords: csv
Platform: UNKNOWN
